jupyterlab/.DS_Store
jupyterlab/__init__.py
jupyterlab/__main__.py
jupyterlab/_version.py
jupyterlab/browser-test.js
jupyterlab/browser_check.py
jupyterlab/commands.py
jupyterlab/coreconfig.py
jupyterlab/debuglog.py
jupyterlab/federated_labextensions.py
jupyterlab/jlpmapp.py
jupyterlab/labapp.py
jupyterlab/labextensions.py
jupyterlab/labhubapp.py
jupyterlab/node-version-check.js
jupyterlab/pytest_plugin.py
jupyterlab/semver.py
jupyterlab/serverextension.py
jupyterlab/style.js
jupyterlab/upgrade_extension.py
jupyterlab/utils.py
jupyterlab/handlers/__init__.py
jupyterlab/handlers/build_handler.py
jupyterlab/handlers/error_handler.py
jupyterlab/handlers/extension_manager_handler.py
jupyterlab/schemas/@jupyterlab/application-extension/commands.json
jupyterlab/schemas/@jupyterlab/application-extension/context-menu.json
jupyterlab/schemas/@jupyterlab/application-extension/package.json.orig
jupyterlab/schemas/@jupyterlab/application-extension/property-inspector.json
jupyterlab/schemas/@jupyterlab/application-extension/shell.json
jupyterlab/schemas/@jupyterlab/application-extension/top-bar.json
jupyterlab/schemas/@jupyterlab/apputils-extension/notification.json
jupyterlab/schemas/@jupyterlab/apputils-extension/package.json.orig
jupyterlab/schemas/@jupyterlab/apputils-extension/palette.json
jupyterlab/schemas/@jupyterlab/apputils-extension/print.json
jupyterlab/schemas/@jupyterlab/apputils-extension/sanitizer.json
jupyterlab/schemas/@jupyterlab/apputils-extension/themes.json
jupyterlab/schemas/@jupyterlab/apputils-extension/workspaces.json
jupyterlab/schemas/@jupyterlab/cell-toolbar-extension/package.json.orig
jupyterlab/schemas/@jupyterlab/cell-toolbar-extension/plugin.json
jupyterlab/schemas/@jupyterlab/codemirror-extension/commands.json
jupyterlab/schemas/@jupyterlab/codemirror-extension/package.json.orig
jupyterlab/schemas/@jupyterlab/collaboration-extension/package.json.orig
jupyterlab/schemas/@jupyterlab/collaboration-extension/user-menu-bar.json
elixirnote-4.0.0a30.dist-info/METADATA
elixirnote-4.0.0a30.dist-info/WHEEL
elixirnote-4.0.0a30.dist-info/entry_points.txt
elixirnote-4.0.0a30.dist-info/licenses/LICENSE
elixirnote-4.0.0a30.dist-info/RECORD
