Metadata-Version: 2.1
Name: elixirnote
Version: 4.0.0a30
Summary: go from data to knowledge
Project-URL: Homepage, https://ciusji.gitbook.io/elixirnote/
Project-URL: Documentation, https://ciusji.gitbook.io/elixirnote/
Project-URL: Source, https://github.com/ElixirNote/elixirnote
Project-URL: Issues, https://github.com/ElixirNote/elixirnote/issues
Project-URL: Pypi, https://pypi.org/project/elixirnote/
Author-email: ciusji <bqjimaster@gmail.com>
License: Copyright (c) 2015-2022 Project Jupyter Contributors
License-File: LICENSE
Keywords: elixirnote,ipython,jupyter
Classifier: Development Status :: 5 - Production/Stable
Classifier: Framework :: Jupyter
Classifier: Framework :: Jupyter :: JupyterLab
Classifier: Framework :: Jupyter :: JupyterLab :: 4
Classifier: Intended Audience :: Developers
Classifier: Intended Audience :: Science/Research
Classifier: Intended Audience :: System Administrators
Classifier: License :: OSI Approved :: BSD License
Classifier: Programming Language :: Python
Classifier: Programming Language :: Python :: 3.7
Classifier: Programming Language :: Python :: 3.8
Classifier: Programming Language :: Python :: 3.9
Classifier: Programming Language :: Python :: 3.10
Requires-Python: >=3.7
Requires-Dist: elixir-shim>=0.2.2
Requires-Dist: elixirlab-server>=2.16.5
Requires-Dist: importlib-metadata>=3.6; python_version < '3.10'
Requires-Dist: importlib-resources>=1.4; python_version < '3.9'
Requires-Dist: ipykernel
Requires-Dist: jinja2>=3.0.3
Requires-Dist: jupyter-core
Requires-Dist: jupyter-server-ydoc<0.2.0,>=0.1.9
Requires-Dist: packaging
Requires-Dist: tomli
Requires-Dist: tornado>=6.1.0
Requires-Dist: ypy-websocket
Provides-Extra: dev
Requires-Dist: build; extra == 'dev'
Requires-Dist: coverage; extra == 'dev'
Requires-Dist: hatchling; extra == 'dev'
Requires-Dist: pre-commit; extra == 'dev'
Requires-Dist: pytest-cov; extra == 'dev'
Provides-Extra: docs
Requires-Dist: jsx-lexer; extra == 'docs'
Requires-Dist: myst-parser; extra == 'docs'
Requires-Dist: pydata-sphinx-theme; extra == 'docs'
Requires-Dist: pytest; extra == 'docs'
Requires-Dist: pytest-check-links; extra == 'docs'
Requires-Dist: pytest-tornasync; extra == 'docs'
Requires-Dist: sphinx-copybutton; extra == 'docs'
Requires-Dist: sphinx>=1.8; extra == 'docs'
Provides-Extra: docs-screenshots
Requires-Dist: altair==4.2.0; extra == 'docs-screenshots'
Requires-Dist: ipython==8.0.0; extra == 'docs-screenshots'
Requires-Dist: ipywidgets==7.6.6; extra == 'docs-screenshots'
Requires-Dist: jupyterlab-geojson==3.2.0; extra == 'docs-screenshots'
Requires-Dist: jupyterlab-language-pack-zh-cn==3.2.post7; extra == 'docs-screenshots'
Requires-Dist: matplotlib==3.5.1; extra == 'docs-screenshots'
Requires-Dist: nbconvert>=7.0.0; extra == 'docs-screenshots'
Requires-Dist: pandas==1.3.5; extra == 'docs-screenshots'
Requires-Dist: scipy==1.7.3; extra == 'docs-screenshots'
Requires-Dist: vdom==0.6; extra == 'docs-screenshots'
Requires-Dist: vega-datasets==0.9.0; extra == 'docs-screenshots'
Provides-Extra: test
Requires-Dist: jupyterlab-server[test]<3,>=2.11.1; extra == 'test'
Requires-Dist: pytest-check-links>=0.5; extra == 'test'
Requires-Dist: pytest-console-scripts; extra == 'test'
Requires-Dist: pytest>=6.0; extra == 'test'
Requires-Dist: requests; extra == 'test'
Requires-Dist: requests-cache; extra == 'test'
Requires-Dist: virtualenv; extra == 'test'
Provides-Extra: ui-tests
Requires-Dist: build; extra == 'ui-tests'
